pqinput/__init__.py
pqinput/drawPES.py
pqinput/inpxml.py
pqinput/propagation_dicts.py
pqinput-0.0.415.dist-info/LICENSE.txt
pqinput-0.0.415.dist-info/METADATA
pqinput-0.0.415.dist-info/WHEEL
pqinput-0.0.415.dist-info/top_level.txt
pqinput-0.0.415.dist-info/RECORD
