Metadata-Version: 2.1
Name: pqinput
Version: 0.0.415
Summary: Create input files for QDng calculations
Home-page: https://gitlab.fysik.su.se/lucas.borges/inputxml
Author: Lucas Borges
Author-email: Lucas Borges <lucas.borges@fysik.su.se>
License: MIT
Project-URL: Homepage, https://gitlab.fysik.su.se/lucas.borges/pqinput
Keywords: qdng
Classifier: Programming Language :: Python :: 3
Classifier: License :: OSI Approved :: MIT License
Classifier: Operating System :: OS Independent
Requires-Python: >=3.6
License-File: LICENSE.txt
